CHANGES.txt
LICENSE.txt
MANIFEST.in
README
README.md
README.txt
setup.py
prettyplotlib/__init__.py
prettyplotlib/_bar.py
prettyplotlib/_barh.py
prettyplotlib/_boxplot.py
prettyplotlib/_fill_between.py
prettyplotlib/_fill_betweenx.py
prettyplotlib/_hist.py
prettyplotlib/_legend.py
prettyplotlib/_pcolormesh.py
prettyplotlib/_plot.py
prettyplotlib/_scatter.py
prettyplotlib/_scatterhist.py
prettyplotlib/colors.py
prettyplotlib/utils.py
prettyplotlib.egg-info/PKG-INFO
prettyplotlib.egg-info/SOURCES.txt
prettyplotlib.egg-info/dependency_links.txt
prettyplotlib.egg-info/requires.txt
prettyplotlib.egg-info/top_level.txt